{
  "$schema": "https://aka.ms/azure/static-web-apps-cli/schema",
  "configurations": {
    "BlazorSwaTemplate": {
      "appLocation": "BlazorSwaTemplate.Client",
      ////#if (IncludeApi)
      //"apiLocation": "BlazorSwaTemplate.Api",
      ////#endif
      "outputLocation": "bin\\wwwroot",
      "appBuildCommand": "dotnet publish -c Release -o bin",
      ////#if (IncludeApi)
      //"apiBuildCommand": "dotnet publish -c Release",
      ////#endif
      "run": "dotnet watch run",
      "appDevserverUrl": "http://localhost:5110"
    }
  }
}